{
    "Presets": {
        "Underlying container": [
            {
                "first": "c6c40e89-aa98-41f3-a1ab-995171ee99dd",
                "second": {
                    "Name": "Default",
                    "Values": [
                        {
                            "index": 2,
                            "data": {
                                "Name": "Period",
                                "Value": 0.6000000238418579,
                                "Metadata": {
                                    "Bounds": {
                                        "Has min bound": false,
                                        "Min": 0.0,
                                        "Has max bound": false,
                                        "Max": 1.0,
                                        "Drag speed": 0.004000000189989805,
                                        "Use slider": false,
                                        "Is logarithmic": false
                                    }
                                }
                            }
                        }
                    ]
                }
            }
        ]
    }
}