{
    "Presets": {
        "Underlying container": [
            {
                "first": "a8a22010-2b59-44ed-b8c5-1b82524faa02",
                "second": {
                    "Name": "Default",
                    "Values": [
                        {
                            "index": 2,
                            "data": {
                                "Name": "Progression",
                                "Value": 0.5,
                                "Metadata": {
                                    "Bounds": {
                                        "Has min bound": false,
                                        "Min": 0.0,
                                        "Has max bound": false,
                                        "Max": 1.0,
                                        "Drag speed": 0.009999999776482582,
                                        "Use slider": false,
                                        "Is logarithmic": false
                                    }
                                }
                            }
                        },
                        {
                            "index": 2,
                            "data": {
                                "Name": "Fix Artifacts",
                                "Value": 0.0,
                                "Metadata": {
                                    "Bounds": {
                                        "Has min bound": true,
                                        "Min": 0.0,
                                        "Has max bound": true,
                                        "Max": 0.9990000128746033,
                                        "Drag speed": 0.009999999776482582,
                                        "Use slider": true,
                                        "Is logarithmic": false
                                    }
                                }
                            }
                        }
                    ]
                }
            }
        ]
    }
}