{
    "PresetManager": {
        "Presets": {
            "value0": {
                "value0": [
                    {
                        "first": {
                            "value0": {
                                "value0": "efc26819-e254-4c95-aa26-47e6cc6e2bf9"
                            }
                        },
                        "second": {
                            "Name": "10",
                            "Values": [
                                {
                                    "index": 2,
                                    "data": {
                                        "Name": "Nb cells",
                                        "Value": 10.0,
                                        "Metadata": {
                                            "Min Value": 0.0,
                                            "Max Value": 1.0,
                                            "Bounded": false,
                                            "Drag speed": 0.009999999776482582
                                        },
                                        "Default Value": 10.0,
                                        "Default Metadata": {
                                            "Min Value": 0.0,
                                            "Max Value": 1.0,
                                            "Bounded": false,
                                            "Drag speed": 0.009999999776482582
                                        }
                                    }
                                }
                            ]
                        }
                    },
                    {
                        "first": {
                            "value0": {
                                "value0": "bfdbe52a-5d79-4ce6-85b4-340e339798f7"
                            }
                        },
                        "second": {
                            "Name": "2",
                            "Values": [
                                {
                                    "index": 2,
                                    "data": {
                                        "Name": "Nb cells",
                                        "Value": 2.0,
                                        "Metadata": {
                                            "Min Value": 0.0,
                                            "Max Value": 1.0,
                                            "Bounded": false,
                                            "Drag speed": 0.009999999776482582
                                        },
                                        "Default Value": 2.0,
                                        "Default Metadata": {
                                            "Min Value": 0.0,
                                            "Max Value": 1.0,
                                            "Bounded": false,
                                            "Drag speed": 0.009999999776482582
                                        }
                                    }
                                }
                            ]
                        }
                    }
                ]
            }
        }
    }
}