{
    "Presets": {
        "Underlying container": [
            {
                "first": "c74bc4ea-4d9e-4587-b5d7-8ba47ef7a0e2",
                "second": {
                    "Name": "Default",
                    "Values": [
                        {
                            "index": 2,
                            "data": {
                                "Name": "Size",
                                "Value": 1.0,
                                "Metadata": {
                                    "Bounds": {
                                        "Has min bound": true,
                                        "Min": 0.0,
                                        "Has max bound": false,
                                        "Max": 1.0,
                                        "Drag speed": 0.009999999776482582,
                                        "Use slider": false,
                                        "Is logarithmic": false
                                    }
                                }
                            }
                        }
                    ]
                }
            }
        ]
    }
}